__init__.py
sqldatamodel/__init__.py
sqldatamodel/ansicolor.py
sqldatamodel/converters.py
sqldatamodel/exceptions.py
sqldatamodel/htmlparser.py
sqldatamodel/jsonencoder.py
sqldatamodel/optionals.py
sqldatamodel/sqldatamodel.py
sqldatamodel/standarddeviation.py
sqldatamodel/utils.py
sqldatamodel-2.3.2.dist-info/licenses/LICENSE
sqldatamodel-2.3.2.dist-info/METADATA
sqldatamodel-2.3.2.dist-info/WHEEL
sqldatamodel-2.3.2.dist-info/top_level.txt
sqldatamodel-2.3.2.dist-info/RECORD
