Metadata-Version: 2.4
Name: SQLDataModel
Version: 2.3.2
Summary: SQLDataModel is a lightweight dataframe library designed for efficient data extraction, transformation, and loading (ETL) across various sources and destinations, providing an efficient alternative to common setups like pandas, numpy, and sqlalchemy while also providing additional features without the overhead of external dependencies.
Author-email: Ante Tonkovic-Capin <antetc@icloud.com>
License-Expression: MIT
Project-URL: Homepage, https://github.com/AnteT/SQLDataModel
Project-URL: Documentation, https://sqldatamodel.readthedocs.io/en/latest/
Project-URL: Source, https://github.com/AnteT/SQLDataModel.git
Keywords: SQL,ETL,dataframe,terminal-tables,pretty-print-tables,sql2sql,data-analysis,data-science,datamodel,extract,transform,load,web-scraping-tables,data-mining,html,html-table-parsing,apache-arrow,pyarrow,pyarrow-conversion,pyarrow-to-table,pyarrow-to-sql,pyarrow-to-csv,parquet-file-parsing,csv,csv-parsing,markdown,markdown-table-parsing,latex,latex-table-parsing,csv2latex,csv2tex,csvtolatex,delimited,delimited-data-parsing,file-conversion,format-conversion,terminal-styling,table-styling,fro
Classifier: Development Status :: 4 - Beta
Classifier: Intended Audience :: Developers
Classifier: Intended Audience :: Science/Research
Classifier: Operating System :: OS Independent
Classifier: Programming Language :: Python :: 3
Classifier: Programming Language :: Python :: 3.9
Classifier: Programming Language :: Python :: 3.10
Classifier: Programming Language :: Python :: 3.11
Classifier: Programming Language :: Python :: 3.12
Classifier: Programming Language :: Python :: 3.13
Classifier: Programming Language :: Python :: 3.14
Classifier: Topic :: Scientific/Engineering
Requires-Python: >=3.9
License-File: LICENSE
Provides-Extra: dateutil
Requires-Dist: python-dateutil>=2.8.2; extra == "dateutil"
Provides-Extra: numpy
Requires-Dist: numpy>=1.21; extra == "numpy"
Provides-Extra: pandas
Requires-Dist: pandas>=1.3; extra == "pandas"
Provides-Extra: polars
Requires-Dist: polars>=1.0.0; extra == "polars"
Provides-Extra: pyarrow
Requires-Dist: pyarrow>=12.0; extra == "pyarrow"
Provides-Extra: openpyxl
Requires-Dist: openpyxl>=3.0; extra == "openpyxl"
Provides-Extra: all
Requires-Dist: python-dateutil>=2.8.2; extra == "all"
Requires-Dist: numpy>=1.21; extra == "all"
Requires-Dist: pandas>=1.3; extra == "all"
Requires-Dist: polars>=1.0.0; extra == "all"
Requires-Dist: pyarrow>=12.0; extra == "all"
Requires-Dist: openpyxl>=3.0; extra == "all"
Dynamic: license-file
